{"4890964_1742141548_34_11001_10": {"uids": ["2136421725", "1146309316", "1654730251", "124050232", "1757397958", "1293550187", "455701121", "1472087532", "254796599", "1388336424", "552129180", "1579766832"], "game_mode": "Quick Play", "replay": "10331333517", "mvp": "124050232", "mvp_char": "CloakDagger", "svp": "1579766832", "svp_char": "AdamWarlock", "players": [{"2136421725": {"handle": "SockboiGamer", "team": 1, "last": "DrStrange", "won": 1, "kos": 15, "deaths": 3, "assists": 1, "total_damage": 15343.51440167427, "total_taken": 18434.4063744545, "total_heal": 0, "badges": [{"name": "Triple!", "id": 6, "count": 1}, {"name": "Relentless Offense", "id": 9, "count": 1}, {"name": "Mighty Vanquisher", "id": 11, "count": 1}], "heroes": [{"hero": "DrStrange", "time": 480.00170156918466, "kos": 15, "deaths": 3, "assists": 1, "acc": 0.5168539325842697}]}}, {"1146309316": {"handle": "80n3s", "team": 1, "last": "Hulk", "won": 1, "kos": 10, "deaths": 4, "assists": 10, "total_damage": 10296.981262922287, "total_taken": 19687.778537750244, "total_heal": 0, "badges": [], "heroes": [{"hero": "Hulk", "time": 480.00170156918466, "kos": 10, "deaths": 4, "assists": 10, "acc": 0.6360153256704981}]}}, {"1654730251": {"handle": "Sepphiroth TM", "team": 1, "last": "Magik", "won": 1, "kos": 10, "deaths": 4, "assists": 0, "total_damage": 14929.545168876648, "total_taken": 7692.401474952698, "total_heal": 0, "badges": [], "heroes": [{"hero": "Punisher", "time": 227.9539168253541, "kos": 2, "deaths": 1, "assists": 0, "acc": 0.27983539094650206}, {"hero": "Magik", "time": 252.04778474383056, "kos": 8, "deaths": 3, "assists": 0, "acc": 0.6081081081081081}]}}, {"124050232": {"handle": "Offensive ID", "team": 1, "last": "CloakDagger", "won": 1, "kos": 12, "deaths": 2, "assists": 16, "total_damage": 6303.2167065143585, "total_taken": 4237.678488969803, "total_heal": 21902.62514257431, "badges": [{"name": "Triple!", "id": 6, "count": 1}, {"name": "Gifted Healer", "id": 12, "count": 1}, {"name": "Trusty Sidekick", "id": 8, "count": 1}, {"name": "MVP", "id": 1, "count": 1}], "heroes": [{"hero": "CloakDagger", "time": 480.00170156918466, "kos": 12, "deaths": 2, "assists": 16, "acc": 0.9565217391304348}]}}, {"1757397958": {"handle": "Se\u00f1or Baz", "team": 1, "last": "AdamWarlock", "won": 1, "kos": 11, "deaths": 4, "assists": 7, "total_damage": 7209.267428398132, "total_taken": 5584.200783729553, "total_heal": 11910.998878955841, "badges": [{"name": "Quad!", "id": 5, "count": 1}], "heroes": [{"hero": "Jeff", "time": 272.61019929498434, "kos": 5, "deaths": 3, "assists": 5, "acc": 0.6666666666666666}, {"hero": "AdamWarlock", "time": 207.39150227420032, "kos": 6, "deaths": 1, "assists": 2, "acc": 0.2608695652173913}]}}, {"1293550187": {"handle": "Mighty_Army", "team": 1, "last": "SpiderMan", "won": 1, "kos": 10, "deaths": 6, "assists": 1, "total_damage": 8652.978719234467, "total_taken": 3928.44513130188, "total_heal": 0, "badges": [], "heroes": [{"hero": "SpiderMan", "time": 297.3169136438519, "kos": 8, "deaths": 4, "assists": 1, "acc": 0.55}, {"hero": "IronMan", "time": 182.68478792533278, "kos": 2, "deaths": 2, "assists": 0, "acc": 0.5555555555555556}]}}, {"455701121": {"handle": "Aboha", "team": 0, "last": "Punisher", "won": 0, "kos": 12, "deaths": 9, "assists": 0, "total_damage": 11859.252531051636, "total_taken": 6981.576691150665, "total_heal": 0, "badges": [], "heroes": [{"hero": "Punisher", "time": 480.00170156918466, "kos": 12, "deaths": 9, "assists": 0, "acc": 0.22502172024326672}]}}, {"1472087532": {"handle": "takesi123", "team": 0, "last": "CloakDagger", "won": 0, "kos": 8, "deaths": 6, "assists": 14, "total_damage": 5040.755502939224, "total_taken": 6696.918454170227, "total_heal": 14257.607270240784, "badges": [], "heroes": [{"hero": "LunaSnow", "time": 30.10228414647281, "kos": 0, "deaths": 1, "assists": 0, "acc": 0.5454545454545454}, {"hero": "CloakDagger", "time": 449.89941742271185, "kos": 8, "deaths": 5, "assists": 14, "acc": 0.8650442477876106}]}}, {"254796599": {"handle": "frenchfri", "team": 0, "last": "RocketRaccoon", "won": 0, "kos": 8, "deaths": 4, "assists": 13, "total_damage": 3450.0862517356873, "total_taken": 6244.631452322006, "total_heal": 13423.58397102356, "badges": [], "heroes": [{"hero": "Magneto", "time": 97.92943564429879, "kos": 2, "deaths": 1, "assists": 0, "acc": 0.47692307692307695}, {"hero": "RocketRaccoon", "time": 382.07226592488587, "kos": 6, "deaths": 3, "assists": 13, "acc": 0.2119815668202765}]}}, {"1388336424": {"handle": "Zer0Mango", "team": 0, "last": "Groot", "won": 0, "kos": 7, "deaths": 6, "assists": 0, "total_damage": 10566.9935836792, "total_taken": 29900.94003033638, "total_heal": 0, "badges": [{"name": "Impentrable Defence", "id": 7, "count": 1}], "heroes": [{"hero": "Groot", "time": 480.00170156918466, "kos": 7, "deaths": 6, "assists": 0, "acc": 0.2867383512544803}]}}, {"552129180": {"handle": "ImZeroStep", "team": 0, "last": "CaptainAmerica", "won": 0, "kos": 8, "deaths": 2, "assists": 0, "total_damage": 9584.325329303741, "total_taken": 19322.348083019257, "total_heal": 16, "badges": [], "heroes": [{"hero": "CaptainAmerica", "time": 480.00170156918466, "kos": 8, "deaths": 2, "assists": 0, "acc": 0.6391304347826087}]}}, {"1579766832": {"handle": "HexOffendr", "team": 0, "last": "AdamWarlock", "won": 0, "kos": 9, "deaths": 8, "assists": 9, "total_damage": 7588.1870765686035, "total_taken": 7566.041365861893, "total_heal": 9870.952118873596, "badges": [{"name": "SVP", "id": 2, "count": 1}], "heroes": [{"hero": "AdamWarlock", "time": 480.00170156918466, "kos": 9, "deaths": 8, "assists": 9, "acc": 0.4025157232704403}]}}]}}