{"4891191_1733780682_3319_11001_10": {"uids": [2136421725, 351245562, 197422226, 1120291517, 438530501, 78969825, 141252281, 1501392297, 1236246739, 1069598011, 616602078, 793567005], "game_mode": "Competitive", "replay": "1086374733", "mvp": 2136421725, "mvp_char": "MoonKnight", "svp": 793567005, "svp_char": "Jeff", "players": [{"2136421725": {"handle": "SockboiGamer", "team": 1, "last": "MoonKnight", "won": 1, "kos": 20, "deaths": 2, "assists": 0, "total_damage": 12300.452319145203, "total_taken": 3547.5622382164, "total_heal": 0, "badges": [], "heroes": [{"hero": "MoonKnight", "time": 454.8301630988717, "kos": 20, "deaths": 2, "assists": 0, "acc": 0.32212581344902386}]}, "badges": [{"name": "Triple!", "id": 6, "count": 1}, {"name": "Relentless Offense", "id": 9, "count": 1}, {"name": "Mighty Vanquisher", "id": 11, "count": 1}, {"name": "MVP", "id": 1, "count": 1}]}, {"351245562": {"handle": "LilMingo99", "team": 1, "last": "Groot", "won": 1, "kos": 13, "deaths": 1, "assists": 1, "total_damage": 9836.900077819824, "total_taken": 26484.333618164062, "total_heal": 0, "badges": [], "heroes": [{"hero": "Groot", "time": 454.8301630988717, "kos": 13, "deaths": 1, "assists": 1, "acc": 0.40487804878048783}]}, "badges": [{"name": "Impentrable Defence", "id": 7, "count": 1}]}, {"197422226": {"handle": "Koufax32", "team": 1, "last": "Jeff", "won": 1, "kos": 0, "deaths": 1, "assists": 23, "total_damage": 252.7175064086914, "total_taken": 362.6664686203003, "total_heal": 16445.42516708374, "badges": [], "heroes": [{"hero": "Jeff", "time": 454.8301630988717, "kos": 0, "deaths": 1, "assists": 23, "acc": 0.2857142857142857}]}, "badges": [{"name": "Gifted Healer", "id": 12, "count": 1}, {"name": "Trusty Sidekick", "id": 8, "count": 1}]}, {"1120291517": {"handle": "Mannee", "team": 1, "last": "IronFist", "won": 1, "kos": 17, "deaths": 3, "assists": 0, "total_damage": 7525.752548217773, "total_taken": 4790.153349876404, "total_heal": 630.8826904296875, "badges": [], "heroes": [{"hero": "IronFist", "time": 454.8301630988717, "kos": 17, "deaths": 3, "assists": 0, "acc": 0.550561797752809}]}, "badges": [{"name": "Triple!", "id": 6, "count": 1}]}, {"438530501": {"handle": "OllieDominate", "team": 1, "last": "ScarletWitch", "won": 1, "kos": 18, "deaths": 3, "assists": 0, "total_damage": 8740.84293627739, "total_taken": 2729.833486557007, "total_heal": 0, "badges": [], "heroes": [{"hero": "ScarletWitch", "time": 454.8301630988717, "kos": 18, "deaths": 3, "assists": 0, "acc": 0.49299533022014674}]}}, {"78969825": {"handle": "Dj2timez1", "team": 1, "last": "CloakDagger", "won": 1, "kos": 8, "deaths": 2, "assists": 20, "total_damage": 2905.450031518936, "total_taken": 2495.1614627838135, "total_heal": 9745.884498596191, "badges": [], "heroes": [{"hero": "CloakDagger", "time": 454.8301630988717, "kos": 8, "deaths": 2, "assists": 20, "acc": 0.9274193548387096}]}}, {"141252281": {"handle": "donut320", "team": 0, "last": "Wolverine", "won": 0, "kos": 0, "deaths": 7, "assists": 1, "total_damage": 1069.1605367660522, "total_taken": 2798.7103431224823, "total_heal": 125.00005340576172, "badges": [], "heroes": [{"hero": "WinterSoldier", "time": 164.41832867264748, "kos": 0, "deaths": 3, "assists": 0, "acc": 0.3333333333333333}, {"hero": "IronFist", "time": 96.15522604621947, "kos": 0, "deaths": 2, "assists": 1, "acc": 0.3}, {"hero": "Wolverine", "time": 141.4136872086674, "kos": 0, "deaths": 2, "assists": 0, "acc": 0.5}]}}, {"1501392297": {"handle": "YouMrDuckk", "team": 0, "last": "Groot", "won": 0, "kos": 3, "deaths": 8, "assists": 0, "total_damage": 8836.299631595612, "total_taken": 6382.613838672638, "total_heal": 0, "badges": [], "heroes": [{"hero": "MoonKnight", "time": 337.17156190797687, "kos": 3, "deaths": 6, "assists": 0, "acc": 0.3438735177865613}, {"hero": "Groot", "time": 117.65860119089484, "kos": 0, "deaths": 2, "assists": 0, "acc": 0.4583333333333333}]}}, {"1236246739": {"handle": "Karno1", "team": 0, "last": "Hawkeye", "won": 0, "kos": 4, "deaths": 7, "assists": 3, "total_damage": 8286.69425201416, "total_taken": 2729.045048713684, "total_heal": 0, "badges": [], "heroes": [{"hero": "Hawkeye", "time": 454.8301630988717, "kos": 4, "deaths": 7, "assists": 3, "acc": 0.3208955223880597}]}}, {"1069598011": {"handle": "DaTrillest409", "team": 0, "last": "Venom", "won": 0, "kos": 4, "deaths": 4, "assists": 2, "total_damage": 10043.108768463135, "total_taken": 21631.023447752, "total_heal": 0, "badges": [], "heroes": [{"hero": "Venom", "time": 454.8301630988717, "kos": 4, "deaths": 4, "assists": 2, "acc": 0.3488865323435843}]}}, {"616602078": {"handle": "RLPhoenix", "team": 0, "last": "CloakDagger", "won": 0, "kos": 4, "deaths": 5, "assists": 6, "total_damage": 2790.2999954223633, "total_taken": 4063.001247406006, "total_heal": 11457.946098804474, "badges": [], "heroes": [{"hero": "CloakDagger", "time": 454.8301630988717, "kos": 4, "deaths": 5, "assists": 6, "acc": 0.8985148514851485}]}}, {"793567005": {"handle": "xXNELSONXx54", "team": 0, "last": "Jeff", "won": 0, "kos": 3, "deaths": 8, "assists": 1, "total_damage": 3474.9388999938965, "total_taken": 5043.996834754944, "total_heal": 8433.218472480774, "badges": [], "heroes": [{"hero": "Jeff", "time": 454.8301630988717, "kos": 3, "deaths": 8, "assists": 1, "acc": 0.7261904761904762}]}, "badges": [{"name": "SVP", "id": 2, "count": 1}]}]}}