{"4891275_1741669473_638_11001_10": {"uids": [1997984618, 1354019431, 1710691733, 924512826, 616312741, 1500689833, 115196171, 158032211, 962748772, 1876156129, 1594819461, 237447641, 172351051], "game_mode": "Quick Play", "replay": "10218627163", "mvp": 237447641, "mvp_char": "Loki", "svp": 1710691733, "svp_char": "SquirrelGirl", "players": [{"1997984618": {"handle": "ttv_broken242", "team": 1, "last": "Punisher", "won": 0, "kos": 3, "deaths": 4, "assists": 0, "total_damage": 2992.664176464081, "total_taken": 6198.67126750946, "total_heal": 40, "badges": [], "heroes": [{"hero": "CaptainAmerica", "time": 79.03480139747262, "kos": 0, "deaths": 1, "assists": 0, "acc": 0.5}, {"hero": "SpiderMan", "time": 67.22855500131845, "kos": 0, "deaths": 1, "assists": 0, "acc": 0}, {"hero": "Punisher", "time": 138.27777084335685, "kos": 3, "deaths": 2, "assists": 0, "acc": 0.26181818181818184}]}}, {"1354019431": {"handle": "GellySmooch", "team": 1, "last": "PeniParker", "won": 0, "kos": 3, "deaths": 6, "assists": 0, "total_damage": 2859.1398973464966, "total_taken": 9043.10029733181, "total_heal": 281.5, "badges": [], "heroes": [{"hero": "Venom", "time": 77.45683766528964, "kos": 0, "deaths": 2, "assists": 0, "acc": 0.1780821917808219}, {"hero": "PeniParker", "time": 207.08428957685828, "kos": 3, "deaths": 4, "assists": 0, "acc": 0.4936708860759494}]}, "badges": [{"name": "Impentrable Defence", "id": 7, "count": 1}]}, {"1710691733": {"handle": "jean.grey", "team": 1, "last": "SquirrelGirl", "won": 0, "kos": 4, "deaths": 5, "assists": 3, "total_damage": 5367.15092086792, "total_taken": 4218.484781265259, "total_heal": 0, "badges": [], "heroes": [{"hero": "Magik", "time": 100.7936118580401, "kos": 0, "deaths": 2, "assists": 0, "acc": 0.5405405405405406}, {"hero": "SquirrelGirl", "time": 183.74751538410783, "kos": 4, "deaths": 3, "assists": 3, "acc": 0.2711864406779661}]}, "badges": [{"name": "SVP", "id": 2, "count": 1}]}, {"924512826": {"handle": "Ibo_dibbo", "team": 1, "last": "SpiderMan", "won": 0, "kos": 1, "deaths": 0, "assists": 0, "total_damage": 154.25, "total_taken": 176, "total_heal": 0, "badges": [], "heroes": [{"hero": "SpiderMan", "time": 24.14882916212082, "kos": 1, "deaths": 0, "assists": 0, "acc": 0}]}}, {"616312741": {"handle": "Kamui_", "team": 1, "last": "Loki", "won": 0, "kos": 1, "deaths": 3, "assists": 3, "total_damage": 3020.518051147461, "total_taken": 2499.148166179657, "total_heal": 5266.433709621429, "badges": [], "heroes": [{"hero": "Loki", "time": 284.5411272421479, "kos": 1, "deaths": 3, "assists": 3, "acc": 0.5051546391752577}]}}, {"1500689833": {"handle": "Shadow Kasheki", "team": 1, "last": "CloakDagger", "won": 0, "kos": 1, "deaths": 5, "assists": 5, "total_damage": 996.6999988555908, "total_taken": 2903.854709625244, "total_heal": 6006.145508289337, "badges": [], "heroes": [{"hero": "CloakDagger", "time": 284.5411272421479, "kos": 1, "deaths": 5, "assists": 5, "acc": 0.7959183673469388}]}, "badges": [{"name": "Gifted Healer", "id": 12, "count": 1}]}, {"115196171": {"handle": "Gerarmarti", "team": 0, "last": "Jeff", "won": 1, "kos": 2, "deaths": 1, "assists": 13, "total_damage": 350, "total_taken": 2683.742301464081, "total_heal": 5639.819251537323, "badges": [], "heroes": [{"hero": "Jeff", "time": 284.5411272421479, "kos": 2, "deaths": 1, "assists": 13, "acc": 0.25}]}, "badges": [{"name": "Trusty Sidekick", "id": 8, "count": 1}]}, {"158032211": {"handle": "Finaldamianxxx", "team": 0, "last": "Thor", "won": 1, "kos": 9, "deaths": 2, "assists": 2, "total_damage": 4101.230761528015, "total_taken": 8080.380687713623, "total_heal": 0, "badges": [], "heroes": [{"hero": "Thor", "time": 284.5411272421479, "kos": 9, "deaths": 2, "assists": 2, "acc": 0.4430379746835443}]}}, {"962748772": {"handle": "Yamamomo", "team": 0, "last": "SpiderMan", "won": 1, "kos": 14, "deaths": 1, "assists": 6, "total_damage": 3954.0068531036377, "total_taken": 1820.6495819091797, "total_heal": 0, "badges": [], "heroes": [{"hero": "SpiderMan", "time": 284.5411272421479, "kos": 14, "deaths": 1, "assists": 6, "acc": 0.3333333333333333}]}, "badges": [{"name": "Triple!", "id": 6, "count": 1}]}, {"1876156129": {"handle": "BigTasty1029", "team": 0, "last": "MoonKnight", "won": 1, "kos": 20, "deaths": 1, "assists": 0, "total_damage": 6057.0249218940735, "total_taken": 784.3113822937012, "total_heal": 0, "badges": [], "heroes": [{"hero": "MoonKnight", "time": 284.5411272421479, "kos": 20, "deaths": 1, "assists": 0, "acc": 0.32753623188405795}]}, "badges": [{"name": "Triple!", "id": 6, "count": 1}, {"name": "Mighty Vanquisher", "id": 11, "count": 1}, {"name": "Relentless Offense", "id": 9, "count": 1}]}, {"1594819461": {"handle": "llPONTEll", "team": 0, "last": "Hela", "won": 1, "kos": 11, "deaths": 2, "assists": 0, "total_damage": 5145.2174381017685, "total_taken": 2739.192461013794, "total_heal": 0, "badges": [], "heroes": [{"hero": "Hela", "time": 284.5411272421479, "kos": 11, "deaths": 2, "assists": 0, "acc": 0.3157894736842105}]}}, {"237447641": {"handle": "Helloween7448", "team": 0, "last": "Loki", "won": 1, "kos": 14, "deaths": 1, "assists": 12, "total_damage": 5545.8834619522095, "total_taken": 1828.1466302871704, "total_heal": 4406.386206150055, "badges": [], "heroes": [{"hero": "Loki", "time": 284.5411272421479, "kos": 14, "deaths": 1, "assists": 12, "acc": 0.4827018121911038}]}, "badges": [{"name": "MVP", "id": 1, "count": 1}]}, {"172351051": {"handle": "dtyser", "team": 1, "last": "BlackWidow", "won": 0, "kos": 3, "deaths": 4, "assists": 1, "total_damage": 2546, "total_taken": 1571.1961679458618, "total_heal": 0, "badges": [], "heroes": [{"hero": "BlackWidow", "time": 230.6754750777036, "kos": 3, "deaths": 4, "assists": 1, "acc": 0.4}]}}]}}