{"5513591_1751609474_1309402_11001_12": {"uids": ["1424931403", "328689779", "1316046447", "1315182298", "956014007", "1923240850", "1074712982", "152180281", "506027920", "1323811161", "2136421725", "172351051"], "game_mode": "Quick Play", "replay": "10966855439", "mvp": "1315182298", "mvp_char": "Magneto", "svp": "1074712982", "svp_char": "Punisher", "players": [{"1424931403": {"handle": "SHOCKERRR.", "team": 1, "last": "Loki", "won": 1, "kos": 12, "deaths": 6, "assists": 28, "total_damage": 3106.613315343857, "total_taken": 4931.285429477692, "total_heal": 13025.50474858284, "badges": [{"name": "Trusty Sidekick", "id": 8, "count": 1}], "heroes": [{"hero": "Loki", "time": 674.7048402968794, "kos": 12, "deaths": 6, "assists": 28, "acc": 0.38332058148431525}]}}, {"328689779": {"handle": "Nrocco", "team": 1, "last": "Mantis", "won": 1, "kos": 11, "deaths": 5, "assists": 24, "total_damage": 7810.809650421143, "total_taken": 5581.871454238892, "total_heal": 18963.270751953125, "badges": [{"name": "Gifted Healer", "id": 12, "count": 1}], "heroes": [{"hero": "Mantis", "time": 674.7048402968794, "kos": 11, "deaths": 5, "assists": 24, "acc": 0.3676092544987147}]}}, {"1316046447": {"handle": "Squidmattra", "team": 1, "last": "Hulk", "won": 1, "kos": 17, "deaths": 3, "assists": 6, "total_damage": 7475.20006942749, "total_taken": 22706.918369293213, "total_heal": 0, "badges": [], "heroes": [{"hero": "Hulk", "time": 674.7048402968794, "kos": 17, "deaths": 3, "assists": 6, "acc": 0.2697841726618705}]}}, {"1315182298": {"handle": "ANVBlS", "team": 1, "last": "Magneto", "won": 1, "kos": 21, "deaths": 3, "assists": 2, "total_damage": 12043.060391664505, "total_taken": 19018.28492641449, "total_heal": 0, "badges": [{"name": "Triple!", "id": 6, "count": 1}, {"name": "Quad!", "id": 5, "count": 1}, {"name": "MVP", "id": 1, "count": 1}], "heroes": [{"hero": "Magneto", "time": 674.7048402968794, "kos": 21, "deaths": 3, "assists": 2, "acc": 0.5071428571428571}]}}, {"956014007": {"handle": "Ffreakbobb", "team": 1, "last": "Namor", "won": 1, "kos": 24, "deaths": 6, "assists": 1, "total_damage": 16770.89845764637, "total_taken": 6711.432550907135, "total_heal": 0, "badges": [{"name": "Mighty Vanquisher", "id": 11, "count": 1}], "heroes": [{"hero": "Namor", "time": 671.4436021689326, "kos": 24, "deaths": 6, "assists": 1, "acc": 0.376271186440678}, {"hero": "DrStrange", "time": 3.2612381279468536, "kos": 0, "deaths": 0, "assists": 0, "acc": 0}]}}, {"1923240850": {"handle": "Big tuguye", "team": 1, "last": "IronMan", "won": 1, "kos": 20, "deaths": 4, "assists": 0, "total_damage": 19221.136724233627, "total_taken": 5882.897322177887, "total_heal": 0, "badges": [{"name": "Relentless Offense", "id": 9, "count": 1}], "heroes": [{"hero": "IronMan", "time": 674.7048402968794, "kos": 20, "deaths": 4, "assists": 0, "acc": 0.5306859205776173}]}}, {"1074712982": {"handle": "AvengerDaze", "team": 0, "last": "Punisher", "won": 0, "kos": 17, "deaths": 7, "assists": 0, "total_damage": 17297.07100391388, "total_taken": 7339.227243065834, "total_heal": 0, "badges": [{"name": "Triple!", "id": 6, "count": 1}, {"name": "SVP", "id": 2, "count": 1}], "heroes": [{"hero": "Punisher", "time": 163.90924718044698, "kos": 3, "deaths": 1, "assists": 0, "acc": 0.423407917383821}, {"hero": "MoonKnight", "time": 510.7955931164324, "kos": 14, "deaths": 6, "assists": 0, "acc": 0.36630434782608695}]}}, {"152180281": {"handle": "AvengerGlenny", "team": 0, "last": "RocketRaccoon", "won": 0, "kos": 8, "deaths": 7, "assists": 4, "total_damage": 7539.9562158584595, "total_taken": 9932.113632440567, "total_heal": 4795.11382317543, "badges": [], "heroes": [{"hero": "Punisher", "time": 421.3968087863177, "kos": 7, "deaths": 5, "assists": 0, "acc": 0.18932038834951456}, {"hero": "StarLord", "time": 39.82790496759117, "kos": 0, "deaths": 1, "assists": 0, "acc": 0.17985611510791366}, {"hero": "WinterSoldier", "time": 66.95668923854828, "kos": 0, "deaths": 1, "assists": 0, "acc": 0.3939393939393939}, {"hero": "RocketRaccoon", "time": 146.52343730442226, "kos": 1, "deaths": 0, "assists": 4, "acc": 0.2621951219512195}]}}, {"506027920": {"handle": "SirDeranker", "team": 0, "last": "Wolverine", "won": 0, "kos": 9, "deaths": 4, "assists": 0, "total_damage": 13175.378947734833, "total_taken": 24023.15408039093, "total_heal": 2900.7813720703125, "badges": [{"name": "Impentrable Defence", "id": 7, "count": 1}], "heroes": [{"hero": "PeniParker", "time": 413.9953502397984, "kos": 4, "deaths": 3, "assists": 0, "acc": 0.29051383399209485}, {"hero": "EmmaFrost", "time": 47.229363514110446, "kos": 0, "deaths": 1, "assists": 0, "acc": 0.5882352941176471}, {"hero": "Wolverine", "time": 213.48012654297054, "kos": 5, "deaths": 0, "assists": 0, "acc": 0.5365853658536586}]}}, {"1323811161": {"handle": "Vzqa", "team": 0, "last": "TheThing", "won": 0, "kos": 8, "deaths": 10, "assists": 1, "total_damage": 7852.2607345581055, "total_taken": 14070.399329185486, "total_heal": 181.2877540588379, "badges": [], "heroes": [{"hero": "Magik", "time": 209.80211696960032, "kos": 4, "deaths": 4, "assists": 0, "acc": 0.5813953488372093}, {"hero": "SpiderMan", "time": 1.1050762422382832, "kos": 0, "deaths": 0, "assists": 0, "acc": 0}, {"hero": "Wolverine", "time": 250.31752054207027, "kos": 3, "deaths": 4, "assists": 0, "acc": 0.4}, {"hero": "TheThing", "time": 213.48012654297054, "kos": 1, "deaths": 2, "assists": 1, "acc": 0.3870967741935484}]}}, {"2136421725": {"handle": "SockboiGamer", "team": 0, "last": "Loki", "won": 0, "kos": 8, "deaths": 7, "assists": 10, "total_damage": 4577.179018974304, "total_taken": 5097.002659916878, "total_heal": 15929.897713184357, "badges": [], "heroes": [{"hero": "Loki", "time": 674.7048402968794, "kos": 8, "deaths": 7, "assists": 10, "acc": 0.46474601971190294}]}}, {"172351051": {"handle": "dtyser", "team": 0, "last": "AdamWarlock", "won": 0, "kos": 8, "deaths": 7, "assists": 7, "total_damage": 6385.182160377502, "total_taken": 9086.346649050713, "total_heal": 18854.158420562744, "badges": [], "heroes": [{"hero": "AdamWarlock", "time": 674.7048402968794, "kos": 8, "deaths": 7, "assists": 7, "acc": 0.3025210084033613}]}}]}}