{"5513391_1750136267_1309208_11001_12": {"uids": ["1705672076", "1534082455", "1173318680", "247925087", "1174360317", "609000716", "2042433796", "982576141", "172351051", "2136421725", "283485673", "950556681", "191390762"], "game_mode": "Quick Play", "replay": "10735455513", "mvp": "982576141", "mvp_char": "Ultron", "svp": "1705672076", "svp_char": "Magneto", "players": [{"1705672076": {"handle": ".KBG", "team": 1, "last": "Magneto", "won": 0, "kos": 11, "deaths": 8, "assists": 2, "total_damage": 11552.023092269897, "total_taken": 24553.634404182434, "total_heal": 0, "badges": [{"name": "Impentrable Defence", "id": 7, "count": 1}, {"name": "SVP", "id": 2, "count": 1}], "heroes": [{"hero": "DrStrange", "time": 2.4076493959873915, "kos": 0, "deaths": 0, "assists": 0, "acc": 0}, {"hero": "Venom", "time": 553.401071568951, "kos": 9, "deaths": 7, "assists": 1, "acc": 0.36426456071076013}, {"hero": "Magneto", "time": 127.1834839079529, "kos": 2, "deaths": 1, "assists": 1, "acc": 0.390625}]}}, {"1534082455": {"handle": "PeachSc0nes", "team": 1, "last": "InvisibleWoman", "won": 0, "kos": 6, "deaths": 9, "assists": 12, "total_damage": 5147.360000133514, "total_taken": 14275.62929725647, "total_heal": 12335.373666524887, "badges": [], "heroes": [{"hero": "InvisibleWoman", "time": 682.9922048728913, "kos": 6, "deaths": 9, "assists": 12, "acc": 0.44686648501362397}]}}, {"1173318680": {"handle": "spooderman236", "team": 1, "last": "Psylocke", "won": 0, "kos": 14, "deaths": 13, "assists": 2, "total_damage": 11556.785254001617, "total_taken": 8303.07588672638, "total_heal": 0, "badges": [{"name": "Triple!", "id": 6, "count": 1}], "heroes": [{"hero": "WinterSoldier", "time": 261.17618797160685, "kos": 6, "deaths": 4, "assists": 1, "acc": 0.4782608695652174}, {"hero": "Psylocke", "time": 419.51810023002326, "kos": 8, "deaths": 9, "assists": 1, "acc": 0.25398089171974525}]}}, {"247925087": {"handle": "LoneWolf090", "team": 1, "last": "Ultron", "won": 0, "kos": 9, "deaths": 10, "assists": 3, "total_damage": 10256.34107017517, "total_taken": 9960.006837844849, "total_heal": 4987.529673218727, "badges": [], "heroes": [{"hero": "Magik", "time": 426.33897705189884, "kos": 5, "deaths": 8, "assists": 0, "acc": 0.375}, {"hero": "Ultron", "time": 256.65322782099247, "kos": 4, "deaths": 2, "assists": 3, "acc": 0.2988165680473373}]}}, {"1174360317": {"handle": "Oshawoot", "team": 1, "last": "IronMan", "won": 0, "kos": 12, "deaths": 6, "assists": 1, "total_damage": 12130.318572998047, "total_taken": 15353.642678260803, "total_heal": 0, "badges": [], "heroes": [{"hero": "CaptainAmerica", "time": 369.1617462038994, "kos": 2, "deaths": 3, "assists": 1, "acc": 0.6106870229007634}, {"hero": "IronMan", "time": 313.8304586689919, "kos": 10, "deaths": 3, "assists": 0, "acc": 0.48}]}}, {"609000716": {"handle": "Germ96", "team": 1, "last": "CloakDagger", "won": 0, "kos": 10, "deaths": 9, "assists": 8, "total_damage": 5905.846980333328, "total_taken": 5972.728187561035, "total_heal": 15392.565732002258, "badges": [{"name": "Gifted Healer", "id": 12, "count": 1}], "heroes": [{"hero": "CloakDagger", "time": 682.9922048728913, "kos": 10, "deaths": 9, "assists": 8, "acc": 0.7691082802547771}]}}, {"2042433796": {"handle": "Slothius", "team": 0, "last": "Psylocke", "won": 1, "kos": 31, "deaths": 5, "assists": 0, "total_damage": 12561.446754932404, "total_taken": 6256.617884635925, "total_heal": 0, "badges": [{"name": "Triple!", "id": 6, "count": 1}, {"name": "Mighty Vanquisher", "id": 11, "count": 1}], "heroes": [{"hero": "Psylocke", "time": 682.9922048728913, "kos": 31, "deaths": 5, "assists": 0, "acc": 0.19402985074626866}]}}, {"982576141": {"handle": "Rtexx", "team": 0, "last": "Ultron", "won": 1, "kos": 22, "deaths": 5, "assists": 34, "total_damage": 8712.940105438232, "total_taken": 6804.124973773956, "total_heal": 11085.14926147461, "badges": [{"name": "Trusty Sidekick", "id": 8, "count": 1}, {"name": "MVP", "id": 1, "count": 1}], "heroes": [{"hero": "Ultron", "time": 682.9922048728913, "kos": 22, "deaths": 5, "assists": 34, "acc": 0.2670940170940171}]}}, {"172351051": {"handle": "dtyser", "team": 0, "last": "WinterSoldier", "won": 1, "kos": 22, "deaths": 5, "assists": 20, "total_damage": 14913.80905342102, "total_taken": 11887.785438537598, "total_heal": 0, "badges": [{"name": "Quad!", "id": 5, "count": 1}], "heroes": [{"hero": "MisterFantastic", "time": 5.268136616796255, "kos": 0, "deaths": 0, "assists": 0, "acc": 0}, {"hero": "WinterSoldier", "time": 675.9317961446941, "kos": 22, "deaths": 5, "assists": 20, "acc": 0.3415384615384615}]}}, {"2136421725": {"handle": "SockboiGamer", "team": 0, "last": "RocketRaccoon", "won": 1, "kos": 11, "deaths": 4, "assists": 28, "total_damage": 3638.311502456665, "total_taken": 3336.1301612854004, "total_heal": 10367.334070682526, "badges": [], "heroes": [{"hero": "RocketRaccoon", "time": 682.9922048728913, "kos": 11, "deaths": 4, "assists": 28, "acc": 0.2026315789473684}]}}, {"283485673": {"handle": "KingDerp_", "team": 0, "last": "PeniParker", "won": 1, "kos": 24, "deaths": 3, "assists": 3, "total_damage": 12962.03689289093, "total_taken": 18164.178290367126, "total_heal": 1312.566650390625, "badges": [], "heroes": [{"hero": "PeniParker", "time": 682.9922048728913, "kos": 24, "deaths": 3, "assists": 3, "acc": 0.15723270440251572}]}}, {"950556681": {"handle": "Axipod", "team": 0, "last": "Magik", "won": 1, "kos": 31, "deaths": 5, "assists": 0, "total_damage": 16513.687576293945, "total_taken": 10106.83822131157, "total_heal": 0, "badges": [{"name": "Triple!", "id": 6, "count": 1}, {"name": "Relentless Offense", "id": 9, "count": 1}, {"name": "Mighty Vanquisher", "id": 11, "count": 1}], "heroes": [{"hero": "Magik", "time": 682.9922048728913, "kos": 31, "deaths": 5, "assists": 0, "acc": 0.5135135135135135}]}}, {"191390762": {"handle": "Shadepr1nce", "team": 1, "last": null, "won": 0, "kos": 0, "deaths": 0, "assists": 0, "total_damage": 0, "total_taken": 0, "total_heal": 0, "badges": [], "heroes": []}}]}}