{"5518393_1748756048_1101205_11001_11": {"uids": ["314454426", "1174134259", "740640474", "1045127315", "441325770", "69637422", "1672203791", "618982610", "528478565", "114478939", "2136421725", "172351051"], "game_mode": "Quick Play", "replay": "10935446974", "mvp": "1672203791", "mvp_char": "Thor", "svp": "69637422", "svp_char": "Punisher", "players": [{"314454426": {"handle": "xFrankies", "team": 1, "last": "Jeff", "won": 0, "kos": 8, "deaths": 3, "assists": 12, "total_damage": 7736.869802236557, "total_taken": 4332.482479333878, "total_heal": 18341.34611225128, "badges": [{"name": "Gifted Healer", "id": 12, "count": 1}], "heroes": [{"hero": "Jeff", "time": 516.2640911247581, "kos": 8, "deaths": 3, "assists": 12, "acc": 0.76535650799921}]}}, {"1174134259": {"handle": "Kanasera", "team": 1, "last": "LunaSnow", "won": 0, "kos": 5, "deaths": 7, "assists": 7, "total_damage": 9810.299076080322, "total_taken": 18160.894505500793, "total_heal": 10316.048936247826, "badges": [], "heroes": [{"hero": "EmmaFrost", "time": 247.98018601164222, "kos": 2, "deaths": 3, "assists": 1, "acc": 0.4796747967479675}, {"hero": "LunaSnow", "time": 268.2839051131159, "kos": 3, "deaths": 4, "assists": 6, "acc": 0.4393939393939394}]}}, {"740640474": {"handle": "lolmiggy", "team": 1, "last": "Magneto", "won": 0, "kos": 4, "deaths": 4, "assists": 1, "total_damage": 9917.103137493134, "total_taken": 25252.70427417755, "total_heal": 0, "badges": [], "heroes": [{"hero": "Magneto", "time": 516.2640911247581, "kos": 4, "deaths": 4, "assists": 1, "acc": 0.4175084175084175}]}}, {"1045127315": {"handle": "HolyRose", "team": 1, "last": "Ultron", "won": 0, "kos": 6, "deaths": 6, "assists": 9, "total_damage": 9549.450385093689, "total_taken": 3216.7979753017426, "total_heal": 11172.92798256874, "badges": [], "heroes": [{"hero": "Ultron", "time": 516.2640911247581, "kos": 6, "deaths": 6, "assists": 9, "acc": 0.38065661047027505}]}}, {"441325770": {"handle": "Yaoi Above All", "team": 1, "last": "BlackWidow", "won": 0, "kos": 7, "deaths": 7, "assists": 0, "total_damage": 9083.880760192871, "total_taken": 7117.306374073029, "total_heal": 0, "badges": [], "heroes": [{"hero": "BlackWidow", "time": 516.2640911247581, "kos": 7, "deaths": 7, "assists": 0, "acc": 0.609375}]}}, {"69637422": {"handle": "kambow431", "team": 1, "last": "Punisher", "won": 0, "kos": 16, "deaths": 7, "assists": 1, "total_damage": 15685.979528665543, "total_taken": 6407.845511436462, "total_heal": 0, "badges": [{"name": "Triple!", "id": 6, "count": 1}, {"name": "Relentless Offense", "id": 9, "count": 1}, {"name": "Mighty Vanquisher", "id": 11, "count": 1}, {"name": "SVP", "id": 2, "count": 1}], "heroes": [{"hero": "Punisher", "time": 516.2640911247581, "kos": 16, "deaths": 7, "assists": 1, "acc": 0.37170263788968827}]}}, {"1672203791": {"handle": "LowSeratonin79", "team": 0, "last": "Thor", "won": 1, "kos": 15, "deaths": 4, "assists": 0, "total_damage": 11573.397113800049, "total_taken": 25854.684201717377, "total_heal": 0, "badges": [{"name": "Quad!", "id": 5, "count": 1}, {"name": "Impentrable Defence", "id": 7, "count": 1}, {"name": "MVP", "id": 1, "count": 1}], "heroes": [{"hero": "Thor", "time": 516.2640911247581, "kos": 15, "deaths": 4, "assists": 0, "acc": 0.28484848484848485}]}}, {"618982610": {"handle": "Rigged100", "team": 0, "last": "MisterFantastic", "won": 1, "kos": 13, "deaths": 3, "assists": 1, "total_damage": 12682.670404434204, "total_taken": 15954.642902612686, "total_heal": 0, "badges": [], "heroes": [{"hero": "MisterFantastic", "time": 516.2640911247581, "kos": 13, "deaths": 3, "assists": 1, "acc": 0.6020942408376964}]}}, {"528478565": {"handle": "Nimsy", "team": 0, "last": "Jeff", "won": 1, "kos": 15, "deaths": 1, "assists": 18, "total_damage": 6713.74232006073, "total_taken": 3992.651613712311, "total_heal": 11490.663087844849, "badges": [], "heroes": [{"hero": "Jeff", "time": 516.2640911247581, "kos": 15, "deaths": 1, "assists": 18, "acc": 0.6606451612903226}]}}, {"114478939": {"handle": "Nokturnalz", "team": 0, "last": "CloakDagger", "won": 1, "kos": 9, "deaths": 0, "assists": 21, "total_damage": 5824.819867134094, "total_taken": 5128.856276988983, "total_heal": 15187.1590051651, "badges": [{"name": "Trusty Sidekick", "id": 8, "count": 1}], "heroes": [{"hero": "CloakDagger", "time": 516.2640911247581, "kos": 9, "deaths": 0, "assists": 21, "acc": 0.89792663476874}]}}, {"2136421725": {"handle": "SockboiGamer", "team": 0, "last": "IronMan", "won": 1, "kos": 9, "deaths": 6, "assists": 1, "total_damage": 12839.981771469116, "total_taken": 5953.667122125626, "total_heal": 0, "badges": [], "heroes": [{"hero": "IronMan", "time": 516.2640911247581, "kos": 9, "deaths": 6, "assists": 1, "acc": 0.4074074074074074}]}}, {"172351051": {"handle": "dtyser", "team": 0, "last": "Ultron", "won": 1, "kos": 13, "deaths": 4, "assists": 12, "total_damage": 4825.805494308472, "total_taken": 6103.819258213043, "total_heal": 11479.429478287697, "badges": [], "heroes": [{"hero": "Ultron", "time": 516.2640911247581, "kos": 13, "deaths": 4, "assists": 12, "acc": 0.3119584055459272}]}}]}}