{"6714323_1740377044_1088_11001_10": {"uids": ["618651469", "1350342252", "1743827994", "1466858976", "1370808776", "671290502", "813868917", "1063320060", "2107004423", "1473828876", "1999422488", "22474097", "1433739833", "172351051"], "game_mode": "Quick Play", "replay": "10329529296", "mvp": "1999422488", "mvp_char": "SquirrelGirl", "svp": "618651469", "svp_char": "Punisher", "players": [{"618651469": {"handle": "Steel Gargoyle", "team": 1, "last": "Punisher", "won": 0, "kos": 5, "deaths": 6, "assists": 0, "total_damage": 6170.469074726105, "total_taken": 2763.5198860168457, "total_heal": 0, "badges": [{"name": "SVP", "id": 2, "count": 1}], "heroes": [{"hero": "Punisher", "time": 266.0696239322424, "kos": 5, "deaths": 6, "assists": 0, "acc": 0.29213483146067415}]}}, {"1350342252": {"handle": "CHUGnDIESEL", "team": 1, "last": null, "won": 0, "kos": 0, "deaths": 0, "assists": 0, "total_damage": 0, "total_taken": 0, "total_heal": 0, "badges": [], "heroes": []}}, {"1743827994": {"handle": "St1ckyDih", "team": 1, "last": "SpiderMan", "won": 0, "kos": 0, "deaths": 0, "assists": 0, "total_damage": 0, "total_taken": 0, "total_heal": 0, "badges": [], "heroes": [{"hero": "SpiderMan", "time": 266.0696239322424, "kos": 0, "deaths": 0, "assists": 0, "acc": 0}]}}, {"1466858976": {"handle": "YN BB", "team": 1, "last": "CloakDagger", "won": 0, "kos": 0, "deaths": 5, "assists": 0, "total_damage": 523.8091259002686, "total_taken": 1389.4000186920166, "total_heal": 0, "badges": [], "heroes": [{"hero": "IronMan", "time": 133.4413671195507, "kos": 0, "deaths": 2, "assists": 0, "acc": 0.14285714285714285}, {"hero": "CloakDagger", "time": 86.93624367006123, "kos": 0, "deaths": 2, "assists": 0, "acc": 0}, {"hero": "SpiderMan", "time": 45.69201314263046, "kos": 0, "deaths": 1, "assists": 0, "acc": 0.2857142857142857}]}}, {"1370808776": {"handle": "Baller1five", "team": 1, "last": "TheThing", "won": 0, "kos": 3, "deaths": 6, "assists": 1, "total_damage": 3295.876365661621, "total_taken": 7847.151265144348, "total_heal": 0, "badges": [{"name": "Impentrable Defence", "id": 7, "count": 1}], "heroes": [{"hero": "TheThing", "time": 266.0696239322424, "kos": 3, "deaths": 6, "assists": 1, "acc": 0.4342105263157895}]}}, {"671290502": {"handle": "LonggD", "team": 1, "last": "WinterSoldier", "won": 0, "kos": 2, "deaths": 5, "assists": 0, "total_damage": 2956.9036598205566, "total_taken": 2671.3000679016113, "total_heal": 0, "badges": [], "heroes": [{"hero": "WinterSoldier", "time": 266.0696239322424, "kos": 2, "deaths": 5, "assists": 0, "acc": 0.42028985507246375}]}}, {"813868917": {"handle": "yeahtonio", "team": 0, "last": "Psylocke", "won": 1, "kos": 14, "deaths": 1, "assists": 0, "total_damage": 4461.955587863922, "total_taken": 1676.0467376708984, "total_heal": 0, "badges": [], "heroes": [{"hero": "Psylocke", "time": 266.0696239322424, "kos": 14, "deaths": 1, "assists": 0, "acc": 0.42213114754098363}]}}, {"1063320060": {"handle": "SADHANDJCB", "team": 0, "last": "LunaSnow", "won": 1, "kos": 6, "deaths": 1, "assists": 4, "total_damage": 889.1169509887695, "total_taken": 1591.356113433838, "total_heal": 4578.965957283974, "badges": [], "heroes": [{"hero": "LunaSnow", "time": 266.0696239322424, "kos": 6, "deaths": 1, "assists": 4, "acc": 0.3125}]}}, {"2107004423": {"handle": "eatyourkarma", "team": 0, "last": "RocketRaccoon", "won": 1, "kos": 3, "deaths": 2, "assists": 6, "total_damage": 570.3468470573425, "total_taken": 690.1605396270752, "total_heal": 5396.592636346817, "badges": [{"name": "Trusty Sidekick", "id": 8, "count": 1}, {"name": "Gifted Healer", "id": 12, "count": 1}], "heroes": [{"hero": "RocketRaccoon", "time": 266.0696239322424, "kos": 3, "deaths": 2, "assists": 6, "acc": 0.16666666666666666}]}}, {"1473828876": {"handle": "AnaxCepheus", "team": 0, "last": "TheThing", "won": 1, "kos": 10, "deaths": 1, "assists": 0, "total_damage": 3444.4718322753906, "total_taken": 7461.340685367584, "total_heal": 0, "badges": [], "heroes": [{"hero": "TheThing", "time": 266.0696239322424, "kos": 10, "deaths": 1, "assists": 0, "acc": 0.4166666666666667}]}}, {"1999422488": {"handle": "Senrii", "team": 0, "last": "SquirrelGirl", "won": 1, "kos": 18, "deaths": 2, "assists": 4, "total_damage": 8391.627445220947, "total_taken": 2541.626085281372, "total_heal": 0, "badges": [{"name": "Triple!", "id": 6, "count": 1}, {"name": "Mighty Vanquisher", "id": 11, "count": 1}, {"name": "Relentless Offense", "id": 9, "count": 1}, {"name": "MVP", "id": 1, "count": 1}], "heroes": [{"hero": "SquirrelGirl", "time": 266.0696239322424, "kos": 18, "deaths": 2, "assists": 4, "acc": 0.4444444444444444}]}}, {"22474097": {"handle": "ImaniFroggie", "team": 0, "last": "Magik", "won": 1, "kos": 11, "deaths": 2, "assists": 0, "total_damage": 2633.024517059326, "total_taken": 2355.3907775878906, "total_heal": 0, "badges": [], "heroes": [{"hero": "Magik", "time": 266.0696239322424, "kos": 11, "deaths": 2, "assists": 0, "acc": 0.4857142857142857}]}}, {"1433739833": {"handle": "Lionpaw_MR", "team": 1, "last": "Hawkeye", "won": 0, "kos": 1, "deaths": 7, "assists": 3, "total_damage": 2561.118637084961, "total_taken": 3885.186975955963, "total_heal": 2253.2366943359375, "badges": [], "heroes": [{"hero": "Hawkeye", "time": 103.17621582560241, "kos": 0, "deaths": 3, "assists": 0, "acc": 0.3125}, {"hero": "Mantis", "time": 155.56248929165304, "kos": 1, "deaths": 4, "assists": 3, "acc": 0.3950617283950617}]}}, {"172351051": {"handle": "dtyser", "team": 1, "last": "RocketRaccoon", "won": 0, "kos": 0, "deaths": 2, "assists": 4, "total_damage": 807.7440757751465, "total_taken": 1833.9849667549133, "total_heal": 4889.007598638535, "badges": [], "heroes": [{"hero": "RocketRaccoon", "time": 248.99738964438438, "kos": 0, "deaths": 2, "assists": 4, "acc": 0.21524663677130046}]}}]}}